comeit/CHANGELOG.md
comeit/__init__.py
comeit/__main__.py
comeit/checks/body.py
comeit/checks/footer.py
comeit/checks/header.py
comeit/commit_message.py
comeit/default_rules.yml
comeit/logger.py
comeit/parse_args.py
comeit/rules/rule.py
comeit/rules/rule_creator.py
comeit/rules/rule_loader.py
comeit/rules/rule_manager.py
comeit/tests/rule_creator/test_rule_creator.py
comeit/tests/rule_loader/rules.yml
comeit/tests/rule_loader/test_load_rules.py
comeit/tests/test_commit_message.py
comeit/version.py
comeit-0.5.1.dist-info/METADATA
comeit-0.5.1.dist-info/WHEEL
comeit-0.5.1.dist-info/entry_points.txt
comeit-0.5.1.dist-info/RECORD
